main.py
code_discovery-0.2.3.dist-info/licenses/LICENSE
core/__init__.py
core/models.py
core/orchestrator.py
detectors/__init__.py
detectors/base.py
detectors/dotnet.py
detectors/java_micronaut.py
detectors/java_spring.py
detectors/python_fastapi.py
detectors/python_flask.py
enrichers/__init__.py
enrichers/base.py
enrichers/dotnet_enricher.py
enrichers/endpoint_enricher.py
enrichers/java_micronaut_enricher.py
enrichers/java_spring_enricher.py
enrichers/python_fastapi_enricher.py
enrichers/python_flask_enricher.py
generators/__init__.py
generators/openapi_generator.py
parsers/__init__.py
parsers/base.py
parsers/dotnet_parser.py
parsers/fastapi_parser.py
parsers/flask_parser.py
parsers/java_micronaut_parser.py
parsers/java_spring_parser.py
utils/__init__.py
utils/api_client.py
utils/apisec_config.py
utils/build_parsers.py
utils/config.py
utils/state_manager.py
vcs/__init__.py
vcs/base.py
vcs/circleci.py
vcs/factory.py
vcs/github.py
vcs/gitlab.py
vcs/harness.py
vcs/jenkins.py
code_discovery-0.2.3.dist-info/METADATA
code_discovery-0.2.3.dist-info/WHEEL
code_discovery-0.2.3.dist-info/entry_points.txt
code_discovery-0.2.3.dist-info/top_level.txt
code_discovery-0.2.3.dist-info/RECORD
