Metadata-Version: 2.4
Name: code-discovery
Version: 0.2.3
Summary: Automatic API discovery system for multiple frameworks and VCS platforms
Home-page: https://github.com/yourusername/codediscovery
Author: Code Discovery Team
Author-email: team@codediscovery.dev
Project-URL: Bug Reports, https://github.com/yourusername/codediscovery/issues
Project-URL: Source, https://github.com/yourusername/codediscovery
Project-URL: Documentation, https://docs.code-discovery.io
Keywords: api,openapi,swagger,documentation,discovery,spring-boot,fastapi,flask,micronaut,aspnet
Classifier: Development Status :: 4 - Beta
Classifier: Intended Audience :: Developers
Classifier: Topic :: Software Development :: Code Generators
Classifier: Topic :: Software Development :: Documentation
Classifier: Topic :: Software Development :: Quality Assurance
Classifier: License :: OSI Approved :: MIT License
Classifier: Operating System :: OS Independent
Classifier: Programming Language :: Python :: 3
Classifier: Programming Language :: Python :: 3.9
Classifier: Programming Language :: Python :: 3.10
Classifier: Programming Language :: Python :: 3.11
Classifier: Programming Language :: Python :: 3.12
Classifier: Framework :: FastAPI
Classifier: Framework :: Flask
Requires-Python: >=3.9
License-File: LICENSE
Requires-Dist: pyyaml>=6.0.1
Requires-Dist: requests>=2.31.0
Requires-Dist: python-dotenv>=1.0.0
Requires-Dist: astroid>=3.0.0
Requires-Dist: javalang>=0.13.0
Requires-Dist: tree-sitter>=0.20.4
Requires-Dist: tree-sitter-python>=0.20.4
Requires-Dist: tree-sitter-java>=0.20.2
Requires-Dist: pydantic>=2.5.0
Requires-Dist: jsonschema>=4.20.0
Requires-Dist: typing-extensions>=4.9.0
Requires-Dist: PyGithub>=2.1.1
Requires-Dist: python-gitlab>=4.4.0
Requires-Dist: pytest>=7.4.3
Requires-Dist: pytest-cov>=4.1.0
Requires-Dist: pytest-mock>=3.12.0
Requires-Dist: black>=23.12.0
Requires-Dist: flake8>=6.1.0
Requires-Dist: mypy>=1.7.1
Requires-Dist: isort>=5.13.2
Provides-Extra: dev
Requires-Dist: pytest>=7.4.3; extra == "dev"
Requires-Dist: pytest-cov>=4.1.0; extra == "dev"
Requires-Dist: pytest-mock>=3.12.0; extra == "dev"
Requires-Dist: black>=23.12.0; extra == "dev"
Requires-Dist: flake8>=6.1.0; extra == "dev"
Requires-Dist: mypy>=1.7.1; extra == "dev"
Requires-Dist: isort>=5.13.2; extra == "dev"
Requires-Dist: pre-commit>=3.5.0; extra == "dev"
Dynamic: author
Dynamic: author-email
Dynamic: classifier
Dynamic: description
Dynamic: description-content-type
Dynamic: home-page
Dynamic: keywords
Dynamic: license-file
Dynamic: project-url
Dynamic: provides-extra
Dynamic: requires-dist
Dynamic: requires-python
Dynamic: summary
